LICENSE.txt
README.md
requirements.txt
setup.py
appoptics/__init__.py
appoptics/appoptics_noop.py
appoptics/appoptics_test.py
appoptics/async.py
appoptics/djangoware.py
appoptics/imports.py
appoptics/inst_django_orm.py
appoptics/inst_django_templates.py
appoptics/inst_httplib.py
appoptics/inst_memcache.py
appoptics/inst_pymongo.py
appoptics/inst_redis.py
appoptics/inst_sqlalchemy.py
appoptics/json_encoder.py
appoptics/loader.py
appoptics/middleware.py
appoptics/skeleton.py
appoptics/tornado_oboe.py
appoptics/util.py
appoptics.egg-info/PKG-INFO
appoptics.egg-info/SOURCES.txt
appoptics.egg-info/dependency_links.txt
appoptics.egg-info/requires.txt
appoptics.egg-info/top_level.txt
appoptics/bson/bson.h
appoptics/bson/platform_hacks.h
appoptics/swig/VERSION
appoptics/swig/__init__.py
appoptics/swig/_oboe.cpython-34m.so
appoptics/swig/gen_bindings.sh
appoptics/swig/liboboe-1.0-x86_64.so.0.0.0
appoptics/swig/liboboe-1.0.so
appoptics/swig/liboboe-1.0.so.0
appoptics/swig/oboe.h
appoptics/swig/oboe.hpp
appoptics/swig/oboe.i
appoptics/swig/oboe.py
appoptics/swig/oboe_debug.h
appoptics/swig/oboe_wrap.cxx