Metadata-Version: 1.1
Name: appoptics
Version: 2.0.5
Summary: AppOptics libraries, instrumentation, and web middleware components for WSGI, Django, and Tornado.
Home-page: https://www.appoptics.com/monitor/python-performance
Author: SolarWinds, LLC
Author-email: support@appoptics.com
License: LICENSE.txt
Download-URL: https://pypi.python.org/pypi/appoptics
Keywords: appoptics traceview tracelytics oboe liboboe instrumentation performance wsgi middleware django
Platform: UNKNOWN
